discord/ext/i17n/__init__.py
discord/ext/i17n/agent.py
discord/ext/i17n/cache.py
discord/ext/i17n/language.py
discord/ext/i17n/preprocess.py
discord_ext_i17n-0.1.0.dist-info/tests/test_agent.py
discord_ext_i17n-0.1.0.dist-info/tests/test_cache.py
discord_ext_i17n-0.1.0.dist-info/tests/test_def_trans.py
discord_ext_i17n-0.1.0.dist-info/tests/test_language.py
discord_ext_i17n-0.1.0.dist-info/tests/test_preprocess.py
discord_ext_i17n-0.1.0.dist-info/tests/utils.py
discord_ext_i17n-0.1.0.dist-info/METADATA
discord_ext_i17n-0.1.0.dist-info/WHEEL
discord_ext_i17n-0.1.0.dist-info/top_level.txt
discord_ext_i17n-0.1.0.dist-info/RECORD
