Metadata-Version: 2.1
Name: discord-ext-i17n
Version: 0.1.0
Summary: A Pycord extension to support automatic text translations in 107 languages.
Author: Timo
Project-URL: Homepage, https://github.com/timoo4devv/discord-ext-i17n
Project-URL: Bug Tracker, https://github.com/timoo4devv/discord-ext-i17n/issues
Classifier: Intended Audience :: Developers
Classifier: License :: OSI Approved :: MIT License
Classifier: Operating System :: OS Independent
Classifier: Natural Language :: English
Classifier: Programming Language :: Python :: 3.7
Classifier: Programming Language :: Python :: 3.10
Classifier: Programming Language :: Python :: 3.11
Requires-Python: >=3.7
